{
    "en": {
        "build-his-profile": "Build his profile",
        "about-him": "About him",
        "Adelantos":"Advances",
        "algo-salio-mal":"Oops something went wrong",
        "opcion-proceso-solicitud" :"(Select an option to start your application process or display your processes)",
        "solicitud-anticipo-apoyo":"Request for advance and support",
        "solicitar-anticipos-nomina":"Payroll advance request",
        "procesos-anticipos":"Advance Payment Processes",
        "revisar-proceso-anticipo":"You will be able to review the status of your payroll advance",
        "Formulario-alta-adelanto":"Prepayment Request Form",
        "datos-adelanto": "(The required information is subject to change during the authorization process)",
        "monto":"Amount",
        "Descripcion-motivo":"Reason for Request",
        "select-predeterminado":"SELECT AN OPTION",
        "prestamo":"Loan",
        "apoyo":"Support",
        "tiempo-pagos-parcialidad":"Partial Payment Schedule",
        "mensualidad": "Monthly",
        "bimestral": "Bimonthly",
        "trimestral": "Quarterly",
        "numero-pagos-parcialidad": "Number of Partial Payments",
        "monto-pago-parcialidad": "Partial Payment Amount",
        "enviar-solicitud": "Submit request",
        "proceso-actual": "Current Process",
        "descripcion-proceso": "The current process is displayed.",
        "id-anticipo": "Advance ID",
        "motivo": "Reason",
        "en-espera": "Waiting for the process",
        "btn-confirm": "Confirm",
        "btn-sent": "Send Request",
        "procesos": "Processes",
        "ventas-alta": "Sales High",
        "subdirección-autoriza-anticipo": "Subdirector Authorizes Advance",
        "d.c.-autoriza-anticipo-": "D.C. Authorizes Advance",
        "subdirección-autoriza-anticipo-con-evidencia-reafirmar-monto": "Subdirector Authorizes Advance with Evidence",
        "ventas-autorizado": "Sales Authorized",
        "proceso-contraloría-esperando-confirmación": "Control Process Waiting for Confirmation",
        "internomex":"INTERNOMEX",
        "anticipos-subdirector": "(Subdirector Advance Process)",
        "usuario":"User",
        "puesto": "Position",
        "sede":"Headquarters",
        "comentario":"COMMENT",
        "proceso":"Process",
        "prioridad":"Priority",
        "acciones":"Actions",
        "historial-anticipo":"PAYMENT ADVANCE HISTORY OF:",
        "descuento-no-actualizado": "Unupdated discount",
        "cantidad-correcta": "Correct amount.",
        "cantidad-incorrecta":"Incorrect amount.",
        "cantidad-no-cero":"The amount cannot be zero.",
        "error-comunicarse-proveedor":"Error: Try contacting the provider",
        "factura-subio-correctamente":"The invoice was uploaded successfully",
        "fuera-de-tiempo": "The deadline for submitting your applications has passed.",
        "total-factura-no-coincide":"The invoice total does not match the total of the selected commissions.",
        "solicitud-no-completada":"The request could not be completed.",
        "error-sistema":"System error",
        "borrar-anticipo":"Are you sure you want to delete the advance payment for "




        
    },
    "es": {
        "build-his-profile": "Construye su perfil",
        "about-him": "Acerca de",
        "Adelantos":"Adelantos",
        "algo-salio-mal":"Oops, algo salió mal",
        "opcion-proceso-solicitud" :"(Seleccionar una opción para iniciar tu proceso de solicitud o mostrar tus procesos)",
        "solicitud-anticipo-apoyo":"Solicitud Anticipo-Apoyo",
        "solicitar-anticipos-nomina":"Podrás solicitar anticipos de nómina",
        "procesos-anticipos":"Procesos Anticipos",
        "revisar-proceso-anticipo":"Podrás revisar el proceso de tu anticipo de nómina",
        "Formulario-alta-adelanto":"Formulario para alta de adelanto",
        "datos-adelanto": "(Los datos del adelanto pueden cambiar en el proceso de autorización)",
        "monto":"monto",
        "Descripcion-motivo":"Descripción del motivo",
        "select-predeterminado":"SELECCIONA UNA OPCIÓN",
        "prestamo":"Préstamo",
        "apoyo":"Apoyo",
        "tiempo-pagos-parcialidad":"Tiempo de Pagos Parcialidad",
        "mensualidad": "Mensualidad",
        "bimestral": "Bimestral",
        "trimestral": "Trimestral",
        "numero-pagos-parcialidad": "Número de Pagos Parcialidad",
        "monto-pago-parcialidad": "Monto Pago Parcialidad",
        "enviar-solicitud": "Enviar solicitud",
        "proceso-actual": "Proceso actual",
        "descripcion-proceso": "Se muestra el proceso actual.",
        "id-anticipo": "ID anticipo",
        "motivo": "Motivo",
        "en-espera": "En espera del proceso",
        "btn-confirm": "Confirmar",
        "btn-sent": "Enviar solicitud",
        "procesos": "Procesos",
        "ventas-alta": "Ventas alta",
        "subdirección-autoriza-anticipo": "Subdirección autoriza anticipo",
        "d.c.-autoriza-anticipo-": "D.C. autoriza anticipo",
        "subdirección-autoriza-anticipo-con-evidencia-reafirmar-monto": "Subdirección autoriza anticipo con evidencia reafirmar monto",
        "ventas-autorizado": "Ventas autorizado",
        "proceso-contraloría-esperando-confirmación": "Proceso contraloría esperando confirmación",
        "internomex":"INTERNOMEX",
        "anticipos-subdirector": "(Anticipos Proceso subdirector)",
        "usuario":"USUARIO",
        "puesto": "PUESTO",
        "sede":"SEDE",
        "comentario":"Comentario",
        "proceso":"Proceso",
        "prioridad":"Prioridad",
        "acciones":"Acciones",
        "historial-anticipo":"HISTORIAL DEL ANTICIPO DE:",
         "descuento-no-actualizado": "Descuento no actualizado",
         "cantidad-correcta": "Cantidad correcta.",
         "cantidad-incorrecta":"Cantidad incorrecta.",
         "cantidad-no-cero":"Cantidad del monto no puede ser 0.",
         "error-comunicarse-proveedor":"Error: Intente ponerse en contacto con el proveedor",
         "factura-subio-correctamente":"La factura se subio correctamente",
         "fuera-de-tiempo": "Estas fuera de tiempo para enviar tus solicitudes",
         "total-factura-no-coincide":"El total de la factura no coincide con el total de comisiones seleccionadas",
         "solicitud-no-completada":"No se ha podido completar la solicitud",
          "error-sistema":"Error del sistema",
          "borrar-anticipo":"¿Estás seguro que desea borrar el Anticipo de"



    }
}


